skill_ovos_homescreen/LICENSE
skill_ovos_homescreen/MANIFEST.in
skill_ovos_homescreen/README.md
skill_ovos_homescreen/__init__.py
skill_ovos_homescreen/version.py
skill_ovos_homescreen/gui/qt5/AppEntry.qml
skill_ovos_homescreen/gui/qt5/AppsBar.qml
skill_ovos_homescreen/gui/qt5/BottomWidgetsArea.qml
skill_ovos_homescreen/gui/qt5/DayMonthDisplay.qml
skill_ovos_homescreen/gui/qt5/ExamplesDisplay.qml
skill_ovos_homescreen/gui/qt5/HorizontalDisplayLayout.qml
skill_ovos_homescreen/gui/qt5/HorizontalTopArea.qml
skill_ovos_homescreen/gui/qt5/MainPage.qml
skill_ovos_homescreen/gui/qt5/MediaWidgetButton.qml
skill_ovos_homescreen/gui/qt5/MediaWidgetDisplay.qml
skill_ovos_homescreen/gui/qt5/NightTimePage.qml
skill_ovos_homescreen/gui/qt5/NotificationDelegate.qml
skill_ovos_homescreen/gui/qt5/SwipeArea.qml
skill_ovos_homescreen/gui/qt5/TimeDisplay.qml
skill_ovos_homescreen/gui/qt5/VerticalDisplayLayout.qml
skill_ovos_homescreen/gui/qt5/VerticalTopArea.qml
skill_ovos_homescreen/gui/qt5/WeatherArea.qml
skill_ovos_homescreen/gui/qt5/WidgetsArea.qml
skill_ovos_homescreen/gui/qt5/idle.qml
skill_ovos_homescreen/gui/qt5/qmldir
skill_ovos_homescreen/gui/qt5/icons/alarmicon.svg
skill_ovos_homescreen/gui/qt5/icons/cam.svg
skill_ovos_homescreen/gui/qt5/icons/clear.svg
skill_ovos_homescreen/gui/qt5/icons/close.svg
skill_ovos_homescreen/gui/qt5/icons/clouds.svg
skill_ovos_homescreen/gui/qt5/icons/delete.svg
skill_ovos_homescreen/gui/qt5/icons/dialog-close.svg
skill_ovos_homescreen/gui/qt5/icons/down.svg
skill_ovos_homescreen/gui/qt5/icons/fog.svg
skill_ovos_homescreen/gui/qt5/icons/high_temperature.svg
skill_ovos_homescreen/gui/qt5/icons/humidity.svg
skill_ovos_homescreen/gui/qt5/icons/low_temperature.svg
skill_ovos_homescreen/gui/qt5/icons/mic-min.svg
skill_ovos_homescreen/gui/qt5/icons/mic-start.svg
skill_ovos_homescreen/gui/qt5/icons/mic.svg
skill_ovos_homescreen/gui/qt5/icons/moon.svg
skill_ovos_homescreen/gui/qt5/icons/no-internet.svg
skill_ovos_homescreen/ovos_skill_homescreen.egg-info/PKG-INFO
skill_ovos_homescreen/ovos_skill_homescreen.egg-info/SOURCES.txt
skill_ovos_homescreen/ovos_skill_homescreen.egg-info/dependency_links.txt
skill_ovos_homescreen/ovos_skill_homescreen.egg-info/entry_points.txt
skill_ovos_homescreen/ovos_skill_homescreen.egg-info/requires.txt
skill_ovos_homescreen/ovos_skill_homescreen.egg-info/top_level.txt
ovos_skill_homescreen-3.0.3.dist-info/LICENSE
ovos_skill_homescreen-3.0.3.dist-info/METADATA
ovos_skill_homescreen-3.0.3.dist-info/WHEEL
ovos_skill_homescreen-3.0.3.dist-info/entry_points.txt
ovos_skill_homescreen-3.0.3.dist-info/top_level.txt
ovos_skill_homescreen-3.0.3.dist-info/RECORD
