Metadata-Version: 2.1
Name: ovos-skill-homescreen
Version: 3.0.3
Summary: OVOS skill plugin
Home-page: https://github.com/OpenVoiceOS/skill-ovos-homescreen
Author: Aix
Author-email: aix.m@outlook.com
License: Apache-2.0
Keywords: ovos skill plugin
License-File: LICENSE
Requires-Dist: ovos-utils<2.0.0,>=0.0.38
Requires-Dist: ovos-workshop<8.0.0,>=2.4.0
Requires-Dist: ovos-date-parser<1.0.0,>=0.0.3
Requires-Dist: ovos-bus-client<2.0.0,>=1.0.0
